setup.cfg
setup.py
celery_strategy/__init__.py
celery_strategy/strategy.py
celery_strategy/utils.py
celery_strategy.egg-info/PKG-INFO
celery_strategy.egg-info/SOURCES.txt
celery_strategy.egg-info/dependency_links.txt
celery_strategy.egg-info/requires.txt
celery_strategy.egg-info/top_level.txt